fractalcam/__init__.py
fractalcam/fractals.py
fractalcam/cli/__init__.py
fractalcam/cli/main.py
fractalcam-0.1.2.dist-info/LICENSE
fractalcam-0.1.2.dist-info/METADATA
fractalcam-0.1.2.dist-info/WHEEL
fractalcam-0.1.2.dist-info/entry_points.txt
fractalcam-0.1.2.dist-info/top_level.txt
fractalcam-0.1.2.dist-info/RECORD
