Metadata-Version: 2.1
Name: fractalcam
Version: 0.1.2
Summary: Make fractal with USB Webcams
Home-page: https://gitlab.com/ryanmcginger/fractalcam
Author: Ryan McCarthy
Author-email: code@mcginger.net
License: MIT
Keywords: numpy opencv fractal
Platform: UNKNOWN
Classifier: Programming Language :: Python :: 3.8
Requires-Dist: numpy
Requires-Dist: scipy
Requires-Dist: click
Requires-Dist: opencv-python
